VIIRS_orbits/VIIRS_orbits.py
VIIRS_orbits/__init__.py
VIIRS_orbits/credentials.py
VIIRS_orbits/spacetrack_credentials.py
viirs_orbits-1.0.1.dist-info/licenses/LICENSE
viirs_orbits-1.0.1.dist-info/METADATA
viirs_orbits-1.0.1.dist-info/WHEEL
viirs_orbits-1.0.1.dist-info/top_level.txt
viirs_orbits-1.0.1.dist-info/RECORD
